siena_mes/__init__.py
siena_mes-20.1.dist-info/METADATA
siena_mes-20.1.dist-info/WHEEL
siena_mes-20.1.dist-info/RECORD
