Metadata-Version: 2.1
Name: siena-mes
Version: 20.1
Summary: Multimedia Environment for Students
Home-page: https://csis110.com/mes
License: aGPLv3
Author: Robin Flatland
Author-email: flatland@siena.edu
Requires-Python: >=3.10,<4.0
Classifier: License :: Other/Proprietary License
Classifier: Programming Language :: Python :: 3
Classifier: Programming Language :: Python :: 3.10
Classifier: Programming Language :: Python :: 3.11
Requires-Dist: Pillow (>=10.1.0,<11.0.0)
Requires-Dist: numpy (>=1.26.1,<2.0.0)
Requires-Dist: pi-heif (>=0.13.1,<0.14.0)
Requires-Dist: python-resize-image (>=1.1.20,<2.0.0)
Requires-Dist: scipy (>=1.11.3,<2.0.0)
Project-URL: Bug Tracker, https://github.com/Introduction-To-CS-Siena-College/Siena-MES-py/issues
Project-URL: Repository, https://github.com/Introduction-To-CS-Siena-College/Siena-MES-py
